data/__init__.py
data/en.pki
data/load_model.py
data/__pycache__/__init__.cpython-36.pyc
data/__pycache__/load_model.cpython-36.pyc
texttrans/__init__.py
texttrans/texttrans.py
texttrans-1.0.10.dist-info/LICENSE
texttrans-1.0.10.dist-info/METADATA
texttrans-1.0.10.dist-info/WHEEL
texttrans-1.0.10.dist-info/top_level.txt
texttrans-1.0.10.dist-info/RECORD
