Metadata-Version: 2.1
Name: texttrans
Version: 1.0.10
Summary: To computes transition probability of text
Home-page: https://github.com/mitsuharu/text-trans
Author: Mitsuharu Emoto
Author-email: mthr1982+python@gmail.com
License: MIT
Keywords: texttrans,text-trans
Platform: UNKNOWN
Classifier: License :: OSI Approved :: MIT License
Classifier: Programming Language :: Python :: 3.6
